psycopg_infdate/__init__.py
psycopg_infdate-1.0.3.dist-info/LICENSE
psycopg_infdate-1.0.3.dist-info/METADATA
psycopg_infdate-1.0.3.dist-info/WHEEL
psycopg_infdate-1.0.3.dist-info/top_level.txt
psycopg_infdate-1.0.3.dist-info/RECORD
