Metadata-Version: 2.1
Name: psycopg-infdate
Version: 1.0.3
Summary: Support postgresql 'infinity'::DATE in psycopg3
Author-email: Peter Benie <pjb1008@cam.ac.uk>
Project-URL: Homepage, https://gitlab.developers.cam.ac.uk/pjb1008/psycopg-infdate
Project-URL: Bug Tracker, https://gitlab.developers.cam.ac.uk/pjb1008/psycopg-infdate/-/issues
Classifier: Programming Language :: Python :: 3
Classifier: License :: OSI Approved :: GNU Lesser General Public License v3 (LGPLv3)
Classifier: Operating System :: OS Independent
Classifier: Intended Audience :: Developers
Classifier: Topic :: Database
Requires-Python: >=3.7
License-File: LICENSE
Requires-Dist: psycopg (>=3)
